structure.py
my_dsa-1.0.dist-info/METADATA
my_dsa-1.0.dist-info/WHEEL
my_dsa-1.0.dist-info/top_level.txt
my_dsa-1.0.dist-info/RECORD
