Metadata-Version: 2.2
Name: my_dsa
Version: 1.0
Summary: Ultimate Python DSA single-file toolkit
Home-page: https://github.com/Mohitbhosale22062005/my_dsa
Author: Mohit Bhosale
Dynamic: author
Dynamic: description
Dynamic: description-content-type
Dynamic: home-page
Dynamic: summary
